complex_number/__init__.py
complex_number/complex_number.py
tests/__init__.py
tests/test_complex_number.py
complex_number-0.1.3.dist-info/LICENSE
complex_number-0.1.3.dist-info/METADATA
complex_number-0.1.3.dist-info/WHEEL
complex_number-0.1.3.dist-info/top_level.txt
complex_number-0.1.3.dist-info/RECORD
