Metadata-Version: 2.1
Name: complex-number
Version: 0.1.3
Summary: This is a simple complex number python package.
Home-page: https://github.com/Enzo1603/ComplexNumber
Author: Enzo Baraldi
License: MIT
Keywords: python,python 3.10,complex number,complex numbers,complex operations
Classifier: License :: OSI Approved :: MIT License
Classifier: Programming Language :: Python :: 3.10
Classifier: Topic :: Software Development
Classifier: Operating System :: OS Independent
Requires-Python: >=3.10
License-File: LICENSE
